libtvdb/__init__.py
libtvdb/exceptions.py
libtvdb/model/__init__.py
libtvdb/model/actor.py
libtvdb/model/alias.py
libtvdb/model/artwork.py
libtvdb/model/award.py
libtvdb/model/character.py
libtvdb/model/company.py
libtvdb/model/content_rating.py
libtvdb/model/episode.py
libtvdb/model/network.py
libtvdb/model/parsers.py
libtvdb/model/remote_id.py
libtvdb/model/season.py
libtvdb/model/show.py
libtvdb/model/status.py
libtvdb/model/tags.py
libtvdb/model/trailer.py
libtvdb/utilities.py
libtvdb-0.15.0.dist-info/LICENSE
libtvdb-0.15.0.dist-info/METADATA
libtvdb-0.15.0.dist-info/WHEEL
libtvdb-0.15.0.dist-info/RECORD
