Metadata-Version: 2.1
Name: libtvdb
Version: 0.15.0
Summary: A wrapper around the TVDB API.
Home-page: https://github.com/dalemyers/libtvdb
License: MIT
Keywords: tvdb,tv,tv database,tv show
Author: Dale Myers
Author-email: dale@myers.io
Requires-Python: >=3.11,<4.0
Classifier: Development Status :: 4 - Beta
Classifier: Intended Audience :: Developers
Classifier: License :: OSI Approved :: MIT License
Classifier: Programming Language :: Python :: 3
Classifier: Programming Language :: Python :: 3.11
Classifier: Programming Language :: Python :: 3
Classifier: Programming Language :: Python :: 3.11
Classifier: Programming Language :: Python :: 3.12
Classifier: Topic :: Software Development :: Libraries
Requires-Dist: deserialize (>=2.1.0,<3.0.0)
Requires-Dist: httpx (>=0.28.1,<0.29.0)
Requires-Dist: requests (>=2.32.3,<3.0.0)
Project-URL: Repository, https://github.com/dalemyers/libtvdb
